gqlrequests/__init__.py
gqlrequests/builder.py
gqlrequests/py.typed
gqlrequests/pydantic_converter.py
gqlrequests/query_creator.py
gqlrequests-0.0.11.dist-info/LICENSE
gqlrequests-0.0.11.dist-info/METADATA
gqlrequests-0.0.11.dist-info/WHEEL
gqlrequests-0.0.11.dist-info/top_level.txt
gqlrequests-0.0.11.dist-info/RECORD
