Metadata-Version: 2.1
Name: gqlrequests
Version: 0.0.11
Summary: A Python library for making GraphQL requests easier!
Home-page: https://github.com/BeatsuDev/GraphQLRequests
Author: BeatsuDev
Author-email: 
License: MIT
Classifier: Development Status :: 1 - Planning
Classifier: Intended Audience :: Developers
Classifier: License :: OSI Approved :: MIT License
Classifier: Natural Language :: English
Classifier: Operating System :: OS Independent
Classifier: Programming Language :: Python :: 3
Classifier: Topic :: Software Development :: Libraries :: Python Modules
Requires-Python: >=3.8.0
License-File: LICENSE
Requires-Dist: pydantic
